mlflavors/__init__.py
mlflavors/orbit.py
mlflavors/pyod.py
mlflavors/sdv.py
mlflavors/sktime.py
mlflavors/statsforecast.py
mlflavors/version.py
mlflavors/utils/__init__.py
mlflavors/utils/data.py
mlflavors-0.1.0.dist-info/METADATA
mlflavors-0.1.0.dist-info/WHEEL
mlflavors-0.1.0.dist-info/top_level.txt
mlflavors-0.1.0.dist-info/RECORD
