Metadata-Version: 2.1
Name: mlflavors
Version: 0.1.0
Summary: MLflavors: A collection of custom MLflow flavors.
Home-page: https://github.com/ml-toolkits/mlflavors
Author: Benjamin Bluhm
License: BSD-3-Clause
Project-URL: Issue Tracker, https://github.com/ml-toolkits/mlflavors/issues
Project-URL: Documentation, https://mlflavors.readthedocs.io/en/latest/
Keywords: machine-learning ai mlflow
Requires-Python: >=3.7
Requires-Dist: mlflow
Requires-Dist: sktime
Requires-Dist: statsforecast
Requires-Dist: pyod
Requires-Dist: sdv
Provides-Extra: dev
Requires-Dist: datasetsforecast (==0.0.8) ; extra == 'dev'
Requires-Dist: pmdarima ; extra == 'dev'
Requires-Dist: pre-commit ; extra == 'dev'
Requires-Dist: pytest ; extra == 'dev'
Requires-Dist: pytest-cov ; extra == 'dev'
Requires-Dist: setuptools ; extra == 'dev'
Requires-Dist: tomli ; extra == 'dev'
Requires-Dist: nbsphinx (==0.9.1) ; extra == 'dev'
Requires-Dist: numpydoc (==1.5.0) ; extra == 'dev'
Requires-Dist: sphinx-rtd-theme (==1.1.1) ; extra == 'dev'
Requires-Dist: sphinx (==5.3.0) ; extra == 'dev'
Requires-Dist: urllib3 (<2) ; extra == 'dev'
Provides-Extra: orbit
Requires-Dist: orbit-ml ; extra == 'orbit'
